[{"issue_id":7,"name":"revolt.social","id":"64c001d3-1b33-4197-bcaa-82952ea61bcb","short":"The official revolt.social Community","long":"Exchange about revolt.social, bots, servers and other projects built upon the awesome Revolt stack!","tags":["Revolt","Bots","Servers","revolt.social"],"owner_name":"nerrix","owner_id":"01FE5V8NJCKG85KT19Q3ZAYKDZ","invite":"https://app.revolt.chat/invite/SRTSjf0d","users":0,"avatar":"https://revolt.social/img/logo.png"},{"issue_id":8,"name":"Discord Bots","id":"8cc16061-2d01-4944-bcfe-0749a1f61b8b","short":"The Discord Bots (bots.gg) Revolt Community","long":"Not super duper official, but bots.gg-staff run community of Discord Bots (bots.gg)","tags":["Discord","Developers","Bots"],"owner_name":"nerrix","owner_id":"01FE5V8NJCKG85KT19Q3ZAYKDZ","invite":"https://app.revolt.chat/invite/ZE6f9n2Y","users":0,"avatar":"https://autumn.revolt.chat/icons/a-wraIJYwiHe4DcqjHK-MKK5jG7dFVTavKNhqOptlx?max_side=256"},{"issue_id":9,"name":"Revolt Testers","id":"55e947b8-e7a9-40bd-b2d4-91462be095b2","short":"The official revolt.chat Community ","long":"Official Revolt Server - run by Revolt.Chat","tags":["Revolt"],"owner_name":"insert","owner_id":"01EX2NCWQ0CHS3QJF0FEQS1GR4","invite":"https://app.revolt.chat/invite/Testers","users":0,"avatar":"https://autumn.revolt.chat/icons/gtc0gJE2S3RvuDhrl2-JeakvgbqEGr2acvBnRTTh6k?max_side=256"},{"issue_id":10,"name":"Unix","id":"d25efb8f-e61b-42e9-9e89-edcba0816ba8","short":"Linux and Unix related discussions.","long":"Unix Revolt is a server about everything Unix! If you are an enthusiast, or interested about Linux and other Unix or Unix-like systems, feel free to join!","tags":["linux","unix","unix-like","discussions","help"],"owner_name":"aosync","owner_id":"01FD511HD3QEFMH420C5CF6RER","invite":"https://app.revolt.chat/invite/F189TZF5","users":0,"avatar":"https://autumn.revolt.chat/attachments/EcALBtlYNMq5VveQJbFagNlzLaEfy5lz0H4Jkl8H8s/unix-icon.png"},{"issue_id":13,"name":"The Dutch Revolt","id":"e0bfce38-ec35-412d-85e6-e4591f180fde","short":"The first Dutch community on Revolt!","long":"Welcome to the Dutch Revolt! To gain more traction in the Netherlands, we want to present to you the first Revolt server where Dutch is the primary language.","tags":["Dutch","Netherlands","Community","Nederlands","Gezellig","Gezelschap"],"owner_name":"Rik","owner_id":"01FC1HP5X609Y93A9TG9XV6VVX","invite":"https://app.revolt.chat/invite/9emN0y48","users":0,"avatar":"https://autumn.revolt.chat/icons/8JkMex9JpUIeGeNmYy8t8UH7hcESC0G6soRku2IMMl?max_side=256"},{"issue_id":15,"name":"Penguin Chill","id":"88a90afe-7391-4645-a85c-d54f1f1f1afd","short":"A CPPS for chillin with your buds on a rainy day.","long":"Penguin Chill is a fun CPPS with events and new stuff weekly and more dance contests are my fav! ","tags":["CPPS","fun","Gaming","Penguinchill"],"owner_name":"DingDing","owner_id":"01EXAG0ZFX02W7PNQE7W5MT339","invite":"https://app.revolt.chat/invite/BwRPKzQ5","users":0,"avatar":"https://autumn.revolt.chat/icons/uh5rvZ4eNF2fpbFWRzwgjp75Bi2jGPKkS1pyREK9gH"},{"issue_id":16,"name":"soafencord","id":"a5884ac7-e6b3-4233-bbdd-ddf9a1a20d59","short":"official community surrounding soafen as a content creator","long":"a community space for average soafen enjoyers to chat - this compliments the Discord server and Matrix space.","tags":["Gaming","VR","Nintendo","YouTube"],"owner_name":"soafen","owner_id":"01FDTGVHZNNVG221YYC3C75HTB","invite":"https://app.revolt.chat/invite/kFawRVBN","users":0,"avatar":"https://autumn.revolt.chat/icons/aX61VQyDzmJevgLW28wj7UdyNAo-R_1FXOUtnOHn6I"},{"issue_id":17,"name":"KSP World","id":"284fff68-5d67-4863-8bc5-89382cdcb892","short":"The First KR community server & for KeepSOBP viewers","long":"KSP World is the first South Korea community server & for KeepSOBP viewers 👀","tags":["Korea","Korean","Community","Gaming","Developers","Twitch","Streamer","YouTuber"],"owner_name":"Nyan","owner_id":"01FE8A5Z16ZJJSRHT5DEVJ9YSZ","invite":"https://app.revolt.chat/invite/e9z8Zjcm","users":0,"avatar":"https://autumn.revolt.chat/icons/2ntrWqncWuh0M6IX3UXd4t_QQMHFk5hCUXgZNWXy_6"}]